Compiled from "Employee.java"
class Employee {
  java.lang.String name;

  int num;

  public Employee(java.lang.String, int);
    Code:
       0: aload_0
       1: invokespecial #1                  // Method java/lang/Object."<init>":()V
       4: aload_0
       5: aload_1
       6: putfield      #2                  // Field name:Ljava/lang/String;
       9: aload_0
      10: iload_2
      11: putfield      #3                  // Field num:I
      14: return

  public java.lang.String getEmployeeName();
    Code:
       0: aload_0
       1: getfield      #2                  // Field name:Ljava/lang/String;
       4: areturn

  public int getEmployeeNumber();
    Code:
       0: aload_0
       1: getfield      #3                  // Field num:I
       4: ireturn
}
